hexy/__init__.py
hexy/errors.py
hexy/hex_map.py
hexy/hex_tile.py
hexy/hexy.py
Hexy-1.4.4.dist-info/LICENSE.md
Hexy-1.4.4.dist-info/METADATA
Hexy-1.4.4.dist-info/WHEEL
Hexy-1.4.4.dist-info/top_level.txt
Hexy-1.4.4.dist-info/RECORD
